{
    "Ar36": {
        "error": 3.616691251333384e-07,
        "error_type": null,
        "filter_outliers_dict": {
            "filter_outliers": true,
            "iterations": 1,
            "std_devs": 2
        },
        "fit": "linear",
        "value": -6.488181264385063e-06
    },
    "Ar40": {
        "error": 1.5239331170895992e-06,
        "error_type": "SEM",
        "filter_outliers_dict": {
            "filter_outliers": true,
            "iterations": 1,
            "std_devs": 2
        },
        "fit": "linear",
        "value": 9.547852405304797e-05
    }
}