{
    "Ar36": {
        "error": 2.2559703454139186e-05,
        "error_type": "SEM",
        "filter_outliers_dict": {
            "filter_outliers": true,
            "iterations": 1,
            "std_devs": 2
        },
        "fit": "linear",
        "value": -2.139350715980885e-05
    },
    "Ar37": {
        "error": 5.8644749967524284e-05,
        "error_type": "SEM",
        "filter_outliers_dict": {
            "filter_outliers": true,
            "iterations": 1,
            "std_devs": 2
        },
        "fit": "linear",
        "value": -7.287255266156184e-07
    },
    "Ar38": {
        "error": 6.667551849288319e-06,
        "error_type": "SEM",
        "filter_outliers_dict": {
            "filter_outliers": true,
            "iterations": 1,
            "std_devs": 2
        },
        "fit": "linear",
        "value": -4.8243517076935826e-05
    },
    "Ar39": {
        "error": 8.485693366346395e-05,
        "error_type": "SEM",
        "filter_outliers_dict": {
            "filter_outliers": true,
            "iterations": 1,
            "std_devs": 2
        },
        "fit": "linear",
        "value": -5.0097909261968186e-05
    },
    "Ar40": {
        "error": 2.9396428243545867e-05,
        "error_type": "SEM",
        "filter_outliers_dict": {
            "filter_outliers": true,
            "iterations": 1,
            "std_devs": 2
        },
        "fit": "linear",
        "value": -6.259998198102532e-05
    }
}