{
    "H1": {
        "error": 0.0,
        "fit": "default",
        "references": [],
        "value": 1.000645422
    },
    "H3": {
        "error": 0.0,
        "fit": "default",
        "references": [],
        "value": 1.010336772
    },
    "L1": {
        "error": 0.0,
        "fit": "default",
        "references": [],
        "value": 1.001803504
    },
    "L3": {
        "error": 0.0,
        "fit": "default",
        "references": [],
        "value": 1.011568266
    },
    "L5": {
        "error": 0.0,
        "fit": "default",
        "references": [],
        "value": 1.010079043
    }
}