{
    "H1": {
        "error": 1.1538487775812913e-06,
        "error_type": "SEM",
        "filter_outliers_dict": {
            "filter_outliers": true,
            "iterations": 1,
            "std_devs": 2
        },
        "fit": "average",
        "value": -3.6457164982068963e-06
    },
    "H3": {
        "error": 2.5504728131100536e-06,
        "error_type": "SEM",
        "filter_outliers_dict": {
            "filter_outliers": false,
            "iterations": 1,
            "std_devs": 2
        },
        "fit": "average",
        "value": -3.4625023801999993e-06
    },
    "L1": {
        "error": 1.4796066034837163e-06,
        "error_type": "SEM",
        "filter_outliers_dict": {
            "filter_outliers": true,
            "iterations": 1,
            "std_devs": 2
        },
        "fit": "average",
        "value": -2.563649294285714e-06
    },
    "L3": {
        "error": 1.3203805458586874e-06,
        "error_type": "SEM",
        "filter_outliers_dict": {
            "filter_outliers": false,
            "iterations": 1,
            "std_devs": 2
        },
        "fit": "average",
        "value": -3.8090002567e-06
    },
    "L5": {
        "error": 1.8357157683458504e-06,
        "error_type": "SEM",
        "filter_outliers_dict": {
            "filter_outliers": false,
            "iterations": 1,
            "std_devs": 2
        },
        "fit": "average",
        "value": -4.179661299033334e-06
    }
}