{
    "Ar36": {
        "error": 2.8160556121009724e-07,
        "error_type": "",
        "fit": "previous",
        "references": [
            {
                "exclude": false,
                "record_id": "ba-01-N-870"
            }
        ],
        "value": 1.0337609400630213e-06
    },
    "Ar37": {
        "error": 1.8873609262231007e-07,
        "error_type": "",
        "fit": "previous",
        "references": [
            {
                "exclude": false,
                "record_id": "ba-01-N-870"
            }
        ],
        "value": 1.19476699720988e-06
    },
    "Ar38": {
        "error": 2.7365016385795515e-07,
        "error_type": "",
        "fit": "previous",
        "references": [
            {
                "exclude": false,
                "record_id": "ba-01-N-870"
            }
        ],
        "value": -9.357229879635617e-08
    },
    "Ar39": {
        "error": 2.1512647943115778e-07,
        "error_type": "",
        "fit": "previous",
        "references": [
            {
                "exclude": false,
                "record_id": "ba-01-N-870"
            }
        ],
        "value": -1.737464577898489e-07
    },
    "Ar40": {
        "error": 7.262414899387195e-07,
        "error_type": "",
        "fit": "previous",
        "references": [
            {
                "exclude": false,
                "record_id": "ba-01-N-870"
            }
        ],
        "value": 0.0001695212836995279
    }
}