{
    "Ar36": {
        "error": 2.5029270577896545e-07,
        "error_type": "",
        "fit": "previous",
        "references": [
            {
                "exclude": false,
                "record_id": "ba-01-N-1295"
            }
        ],
        "value": 5.344880970529591e-07
    },
    "Ar37": {
        "error": 2.1027624507143475e-07,
        "error_type": "",
        "fit": "previous",
        "references": [
            {
                "exclude": false,
                "record_id": "ba-01-N-1295"
            }
        ],
        "value": 9.894431317538857e-07
    },
    "Ar38": {
        "error": 2.4039773083101733e-07,
        "error_type": "",
        "fit": "previous",
        "references": [
            {
                "exclude": false,
                "record_id": "ba-01-N-1295"
            }
        ],
        "value": 1.9255121723959262e-07
    },
    "Ar39": {
        "error": 2.1522135037933724e-07,
        "error_type": "",
        "fit": "previous",
        "references": [
            {
                "exclude": false,
                "record_id": "ba-01-N-1295"
            }
        ],
        "value": 1.5554503480831181e-07
    },
    "Ar40": {
        "error": 3.858745915426414e-07,
        "error_type": "",
        "fit": "previous",
        "references": [
            {
                "exclude": false,
                "record_id": "ba-01-N-1295"
            }
        ],
        "value": 0.00010965137949346867
    }
}