{
    "Ar36": {
        "error": 1.807264188931461e-07,
        "error_type": "",
        "fit": "previous",
        "references": [
            {
                "exclude": false,
                "record_id": "ba-01-N-1477"
            }
        ],
        "value": 5.337683569633897e-07
    },
    "Ar37": {
        "error": 1.611417987828912e-07,
        "error_type": "",
        "fit": "previous",
        "references": [
            {
                "exclude": false,
                "record_id": "ba-01-N-1477"
            }
        ],
        "value": 7.594207068000737e-07
    },
    "Ar38": {
        "error": 1.76404477884546e-07,
        "error_type": "",
        "fit": "previous",
        "references": [
            {
                "exclude": false,
                "record_id": "ba-01-N-1477"
            }
        ],
        "value": 2.863056777352054e-07
    },
    "Ar39": {
        "error": 1.3966397649981894e-07,
        "error_type": "",
        "fit": "previous",
        "references": [
            {
                "exclude": false,
                "record_id": "ba-01-N-1477"
            }
        ],
        "value": 2.0524852992418105e-07
    },
    "Ar40": {
        "error": 2.2406399784092515e-07,
        "error_type": "",
        "fit": "previous",
        "references": [
            {
                "exclude": false,
                "record_id": "ba-01-N-1477"
            }
        ],
        "value": 6.163335912483245e-05
    }
}